pytri/__init__.py
pytri/version.py
pytri/js/FibersLayer.js
pytri/js/GPUParticleSystem.js
pytri/js/GraphLayer.js
pytri/js/ImageLayer.js
pytri/js/LargeGraphLayer.js
pytri/js/MeshLayer.js
pytri/js/ScatterLayer.js
pytri/js/VolumeLayer.js
pytri/js/substrate.min.js
pytri-0.5.0.dist-info/METADATA
pytri-0.5.0.dist-info/RECORD
pytri-0.5.0.dist-info/WHEEL
pytri-0.5.0.dist-info/top_level.txt
