Metadata-Version: 2.1
Name: pytri
Version: 0.5.0
Summary: Visualize using substrate. For Jupyter notebooks.
Home-page: UNKNOWN
Author: Jordan Matelsky
Author-email: jordan@matelsky.com
License: Apache 2.0
Download-URL: https://github.com/aplbrain/pytri/tarball/0.5.0
Keywords: viz,substrate,3D,visualization
Platform: UNKNOWN
Classifier: Development Status :: 4 - Beta
Classifier: Intended Audience :: Developers
Classifier: Programming Language :: Python :: 3.4
Classifier: Programming Language :: Python :: 3.5
Requires-Dist: mypy
Requires-Dist: typing
Requires-Dist: nose
Requires-Dist: coverage
Requires-Dist: nose-progressive
Requires-Dist: IPython
Requires-Dist: requests
Requires-Dist: networkx
Requires-Dist: numpy
Requires-Dist: pillow
